github_contributions/__init__.py
github_contributions/date.py
github_contributions_python/__init__.py
github_contributions_python/date.py
github_contributions_python-0.1.0.dist-info/LICENSE.md
github_contributions_python-0.1.0.dist-info/METADATA
github_contributions_python-0.1.0.dist-info/WHEEL
github_contributions_python-0.1.0.dist-info/top_level.txt
github_contributions_python-0.1.0.dist-info/RECORD
